yfinance_viz/__init__.py
yfinance_viz/download_stock_history.py
yfinance_viz/transaction_parser.py
yfinance_viz/transactions_visualize.py
yfinance_viz-0.2.0.dist-info/licenses/LICENSE
yfinance_viz-0.2.0.dist-info/METADATA
yfinance_viz-0.2.0.dist-info/WHEEL
yfinance_viz-0.2.0.dist-info/entry_points.txt
yfinance_viz-0.2.0.dist-info/top_level.txt
yfinance_viz-0.2.0.dist-info/RECORD
