Metadata-Version: 2.4
Name: yfinance-viz
Version: 0.2.0
Summary: Yahoo Finance Portfolio Visualizer - A Python tool for downloading and visualizing stock portfolio transactions using Yahoo Finance data
Author-email: ilcavero <ilcavero@gmail.com>
License-Expression: MIT
Project-URL: Repository, https://github.com/ilcavero/yfinance-viz
Project-URL: Homepage, https://github.com/ilcavero/yfinance-viz
Classifier: Programming Language :: Python :: 3
Classifier: Operating System :: OS Independent
Requires-Python: >=3.11
License-File: LICENSE
Requires-Dist: yfinance>=0.2.64
Requires-Dist: plotly>=5.18.0
Requires-Dist: pandas>=2.0.0
Dynamic: license-file
